LICENSE
README.md
setup.py
rrnlp/__init__.py
rrnlp.egg-info/PKG-INFO
rrnlp.egg-info/SOURCES.txt
rrnlp.egg-info/dependency_links.txt
rrnlp.egg-info/not-zip-safe
rrnlp.egg-info/requires.txt
rrnlp.egg-info/top_level.txt
rrnlp/../requirements.txt
rrnlp/models/PICO_tagger.py
rrnlp/models/RCT_classifier.py
rrnlp/models/RoB_classifier.py
rrnlp/models/RoB_classifier_LR.py
rrnlp/models/__init__.py
rrnlp/models/encoder.py
rrnlp/models/ev_inf_classifier.py
rrnlp/models/sample_size_extractor.py
rrnlp/models/study_design_classifier.py
rrnlp/models/util/__init__.py
rrnlp/models/util/index_numbers.py
rrnlp/models/util/schwartz_hearst.py
rrnlp/models/util/minimap/__init__.py
rrnlp/models/util/minimap/cui_to_mh.pck
rrnlp/models/util/minimap/cui_to_mh_supp.pck
rrnlp/models/util/minimap/ignorelist.txt
rrnlp/models/util/minimap/minimap.py
rrnlp/models/util/minimap/prepositions_conjunctions.txt
rrnlp/models/util/minimap/str_to_cui.pck
rrnlp/models/util/minimap/str_to_cui_supp.pck
rrnlp/models/util/minimap/subtrees.pck
rrnlp/models/util/minimap/__pycache__/__init__.cpython-39.pyc
rrnlp/models/util/minimap/__pycache__/minimap.cpython-39.pyc
rrnlp/models/weights/weights_manifest.json