Metadata-Version: 2.1
Name: rrnlp
Version: 1.0.3
Summary: NLP for EBM
Home-page: https://github.com/bwallace/RRnlp
Author: Byron Wallace, Iain Marshall
Author-email: b.wallace@northeastern.edu
License: MIT
Platform: UNKNOWN
License-File: LICENSE
